aoricaan_cli/__init__.py
aoricaan_cli/__main__.py
aoricaan_cli/cli.py
aoricaan_cli/src/__init__.py
aoricaan_cli/src/api/__init__.py
aoricaan_cli/src/api/local.py
aoricaan_cli/src/enpoints/__init__.py
aoricaan_cli/src/enpoints/endpoints.py
aoricaan_cli/src/enpoints/parameters.py
aoricaan_cli/src/lambdas/__init__.py
aoricaan_cli/src/lambdas/configuration.py
aoricaan_cli/src/lambdas/lambdas.py
aoricaan_cli/src/layers/__init__.py
aoricaan_cli/src/layers/layers.py
aoricaan_cli/src/layers/modules.py
aoricaan_cli/src/models/__init__.py
aoricaan_cli/src/models/api_swagger_v2.py
aoricaan_cli/src/models/aws_lambda.py
aoricaan_cli/src/models/cloud_formation.py
aoricaan_cli/src/models/models.py
aoricaan_cli/src/project/__init__.py
aoricaan_cli/src/project/project.py
aoricaan_cli/src/utils/__init__.py
aoricaan_cli/src/utils/api_local.py
aoricaan_cli/src/utils/aws_templates_implementation.py
aoricaan_cli/src/utils/core.py
aoricaan_cli/src/utils/data_types.py
aoricaan_cli/src/utils/debugger.py
aoricaan_cli/src/utils/exeptions.py
aoricaan_cli/src/utils/folders.py
aoricaan_cli/src/utils/generator.py
aoricaan_cli/src/utils/globals.py
aoricaan_cli/src/utils/install_layers.py
aoricaan_cli/src/utils/state.py
aoricaan_cli/src/utils/str_parser.py
aoricaan_cli/src/utils/synth.py
aoricaan_cli/src/utils/templates_generator.py
aoricaan_cli/templates/__init__.py
aoricaan_cli/templates/layers/__init__.py
aoricaan_cli/templates/layers/core/__init__.py
aoricaan_cli/templates/layers/core/python/__init__.py
aoricaan_cli/templates/layers/core/python/core_api/__init__.py
aoricaan_cli/templates/layers/core/python/core_api/responses.py
aoricaan_cli/templates/layers/core/python/core_api/utils.py
aoricaan_cli/templates/layers/core/python/core_aws/__init__.py
aoricaan_cli/templates/layers/core/python/core_aws/s3.py
aoricaan_cli/templates/layers/core/python/core_aws/ssm.py
aoricaan_cli/templates/layers/core/python/core_db/__init__.py
aoricaan_cli/templates/layers/core/python/core_db/base_model.py
aoricaan_cli-0.3.4.dist-info/entry_points.txt
aoricaan_cli-0.3.4.dist-info/WHEEL
aoricaan_cli-0.3.4.dist-info/METADATA
aoricaan_cli-0.3.4.dist-info/RECORD
