Metadata-Version: 2.1
Name: aoricaan-cli
Version: 0.3.4
Summary: 
Author: carlos
Author-email: carlosaarivera23@gmail.com
Requires-Python: >=3.8,<4.0
Classifier: Programming Language :: Python :: 3
Classifier: Programming Language :: Python :: 3.10
Classifier: Programming Language :: Python :: 3.8
Classifier: Programming Language :: Python :: 3.9
Requires-Dist: click-spinner (>=0.1.10,<0.2.0)
Requires-Dist: cookiecutter (>=2.1.1,<3.0.0)
Requires-Dist: fastapi (>=0.78.0,<0.79.0)
Requires-Dist: mangum (>=0.15.0,<0.16.0)
Requires-Dist: pydantic (>=1.8.2,<2.0.0)
Requires-Dist: python-dotenv (>=0.20.0,<0.21.0)
Requires-Dist: tabulate (>=0.8.9,<0.9.0)
Requires-Dist: toml (>=0.10.2,<0.11.0)
Requires-Dist: tqdm (>=4.62.3,<5.0.0)
Requires-Dist: typer[all] (>=0.5.0,<0.6.0)
Requires-Dist: uvicorn (>=0.18.2,<0.19.0)
